xkammd/__init__.py
xkammd/nszbd.py
xkammdmmd-5.2.0.dist-info/METADATA
xkammdmmd-5.2.0.dist-info/RECORD
xkammdmmd-5.2.0.dist-info/WHEEL
xkammdmmd-5.2.0.dist-info/top_level.txt
