Metadata-Version: 2.1
Name: xkammdmmd
Version: 5.2.0
Summary: You know how I love you
Home-page: https://github.com/ricarvy/bbwdxka
Author: LI Jiawei
Author-email: jliea@connect.ust.hk
License: UNKNOWN
Platform: UNKNOWN
Classifier: Programming Language :: Python :: 3
Classifier: License :: OSI Approved :: MIT License
Classifier: Operating System :: OS Independent
